matplot_fmt_pi/__init__.py
matplot_fmt_pi/__init__.pyi
matplot_fmt_pi/py.typed
matplot_fmt_pi/ticker.py
matplot_fmt_pi/ticker.pyi
matplot_fmt_pi-2.1.0.dist-info/LICENSE
matplot_fmt_pi-2.1.0.dist-info/METADATA
matplot_fmt_pi-2.1.0.dist-info/WHEEL
matplot_fmt_pi-2.1.0.dist-info/top_level.txt
matplot_fmt_pi-2.1.0.dist-info/RECORD
