Metadata-Version: 2.1
Name: matplot-fmt-pi
Version: 2.1.0
Summary: Format numbers as multiples of Pi
Home-page: https://github.com/k-donn/format-pi
Author: k-donn
Author-email: k-donn@github.com
License: MIT
Keywords: matplotlib,formatter,locator,axes ticks,numbers,radians,multiples,of,pi
Platform: UNKNOWN
Classifier: License :: OSI Approved :: MIT License
Classifier: Framework :: Matplotlib
Classifier: Programming Language :: Python :: 3 :: Only
Classifier: Programming Language :: Python :: 3
Classifier: Programming Language :: Python :: 3.6
Classifier: Programming Language :: Python :: 3.7
Classifier: Programming Language :: Python :: 3.8
Requires-Dist: numpy
Requires-Dist: matplotlib
